{"is_source_file": true, "format": "JavaScript", "description": "This source file defines a helper function to create and manage a real-time WebSocket client with fallback to polling if WebSocket connection fails or isn't configured. It exports a function `createRealtimeClient` that handles connection lifecycle, message handling, and disconnection.", "external_files": ["../config"], "external_methods": ["getWsUrl"], "published": ["createRealtimeClient"], "classes": [], "methods": [{"name": "createRealtimeClient({ onEvent, onStatus } = {})", "description": "Creates and returns a real-time client object with methods to connect, disconnect, and send messages via WebSocket or fallback to polling.", "scope": "", "scopeKind": ""}], "calls": ["getWsUrl", "WebSocket", "JSON.parse", "JSON.stringify"], "search-terms": ["realtime", "WebSocket", "createRealtimeClient", "ws connection", "polling fallback", "socket events"], "state": 2, "file_id": 18, "knowledge_revision": 55, "git_revision": "c6c012c2672a18d459c8d292fddb02d7565cf480", "ctags": [{"_type": "tag", "name": "createRealtimeClient", "path": "/home/kavia/workspace/code-generation/robot-task-control-panel-3750-3759/robot_runner_gui_frontend/src/api/realtime.js", "pattern": "/^export function createRealtimeClient({ onEvent, onStatus } = {}) {$/", "language": "JavaScript", "kind": "function", "signature": "({ onEvent, onStatus } = {})"}, {"_type": "tag", "name": "data", "path": "/home/kavia/workspace/code-generation/robot-task-control-panel-3750-3759/robot_runner_gui_frontend/src/api/realtime.js", "pattern": "/^          payload = { type: \"message\", data: msg.data };$/", "language": "JavaScript", "kind": "property", "scope": "payload", "scopeKind": "class"}, {"_type": "tag", "name": "payload", "path": "/home/kavia/workspace/code-generation/robot-task-control-panel-3750-3759/robot_runner_gui_frontend/src/api/realtime.js", "pattern": "/^          payload = { type: \"message\", data: msg.data };$/", "language": "JavaScript", "kind": "class"}, {"_type": "tag", "name": "type", "path": "/home/kavia/workspace/code-generation/robot-task-control-panel-3750-3759/robot_runner_gui_frontend/src/api/realtime.js", "pattern": "/^          payload = { type: \"message\", data: msg.data };$/", "language": "JavaScript", "kind": "property", "scope": "payload", "scopeKind": "class"}], "hash": "26980954ca166321fdc7b2b79a45b014", "format-version": 4, "code-base-name": "robot_runner_gui_frontend", "filename": "robot_runner_gui_frontend/src/api/realtime.js", "fields": [{"name": "payload = { type: \"message\", data: msg.data };", "scope": "payload", "scopeKind": "class", "description": "unavailable"}], "revision_history": [{"55": "c6c012c2672a18d459c8d292fddb02d7565cf480"}]}